LICENSE
README.md
setup.py
cpm80/__init__.py
cpm80/bdos.bin
cpm80/ccp.bin
cpm80.egg-info/PKG-INFO
cpm80.egg-info/SOURCES.txt
cpm80.egg-info/dependency_links.txt
cpm80.egg-info/entry_points.txt
cpm80.egg-info/requires.txt
cpm80.egg-info/top_level.txt